devgossip.py
devgossip-1.0.1.dist-info/entry_points.txt
devgossip-1.0.1.dist-info/WHEEL
devgossip-1.0.1.dist-info/METADATA
devgossip-1.0.1.dist-info/RECORD
