Metadata-Version: 2.1
Name: devgossip
Version: 1.0.1
Summary: A simple discussion platform for social communication within the office
License: MIT
Author: Abumere Ogona
Requires-Python: >=3.8,<4.0
Classifier: License :: OSI Approved :: MIT License
Classifier: Programming Language :: Python :: 3
Classifier: Programming Language :: Python :: 3.8
